udunitspy
_udunits2_c
