Metadata-Version: 1.1
Name: udunitspy
Version: 0.0.6
Summary: Python wrapper for UDUNITS2
Home-page: https://github.com/blazetopher/udunitspy/
Author: Christopher Mueller
Author-email: cmueller@asascience.com
License: LICENSE.txt
Platform: UNKNOWN
Classifier:  Intended Audience :: Science/Research
Classifier: Intended Audience :: Developers
Classifier: Intended Audience :: Education
Classifier: Operating System :: OS Independent
Classifier: Programming Language :: Python
Classifier: Topic :: Scientific/Engineering
Classifier: Topic :: Education
Classifier: Topic :: Software Development :: Libraries :: Python Modules
